ignore/__init__.py
ignore/ignore.py
ignore/utils.py
tests/__init__.py
tests/test.py
gitignore_create-0.0.1b0.dist-info/LICENSE
gitignore_create-0.0.1b0.dist-info/METADATA
gitignore_create-0.0.1b0.dist-info/WHEEL
gitignore_create-0.0.1b0.dist-info/entry_points.txt
gitignore_create-0.0.1b0.dist-info/top_level.txt
gitignore_create-0.0.1b0.dist-info/RECORD
