Metadata-Version: 2.1
Name: gitignore-create
Version: 0.0.1b0
Summary: A CLI tool to generate gitignore files
Home-page: https://github.com/iliailmer/gitignore-create
Author: Ilia Ilmer
Author-email: i.ilmer@icloud.com
License: GNU GENERAL PUBLIC LICENSE
Keywords: gitignore git
Platform: UNKNOWN
Requires-Dist: requests
